ratings/__init__.py
ratings/admin.py
ratings/apps.py
ratings/conf.py
ratings/api/__init__.py
ratings/api/serializers/__init__.py
ratings/api/serializers/overallrating.py
ratings/api/serializers/rating.py
ratings/api/serializers/skip_rating.py
ratings/migrations/0001_initial.py
ratings/migrations/__init__.py
ratings/models/__init__.py
ratings/models/interaction.py
ratings/models/overall_rating.py
ratings/models/rating.py
ratings/models/skip_rating.py
tests/__init__.py
tests/settings.py
tests/test_models.py
django_ratings_models-0.1.10.dist-info/AUTHORS.rst
django_ratings_models-0.1.10.dist-info/LICENSE
django_ratings_models-0.1.10.dist-info/METADATA
django_ratings_models-0.1.10.dist-info/WHEEL
django_ratings_models-0.1.10.dist-info/top_level.txt
django_ratings_models-0.1.10.dist-info/RECORD
